mqt/core/__init__.py
mqt/core/__main__.py
mqt/core/_commands.py
mqt/core/_version.py
mqt/core/_version.pyi
mqt/core/dd.cpython-314t-aarch64-linux-gnu.so
mqt/core/dd.pyi
mqt/core/fomac.cpython-314t-aarch64-linux-gnu.so
mqt/core/fomac.pyi
mqt/core/ir.cpython-314t-aarch64-linux-gnu.so
mqt/core/na.cpython-314t-aarch64-linux-gnu.so
mqt/core/py.typed
mqt/core/_compat/__init__.py
mqt/core/_compat/optional.py
mqt/core/_compat/typing.py
mqt/core/include/mqt-core/algorithms/BernsteinVazirani.hpp
mqt/core/include/mqt-core/algorithms/GHZState.hpp
mqt/core/include/mqt-core/algorithms/Grover.hpp
mqt/core/include/mqt-core/algorithms/QFT.hpp
mqt/core/include/mqt-core/algorithms/QPE.hpp
mqt/core/include/mqt-core/algorithms/RandomCliffordCircuit.hpp
mqt/core/include/mqt-core/algorithms/StatePreparation.hpp
mqt/core/include/mqt-core/algorithms/WState.hpp
mqt/core/include/mqt-core/algorithms/mqt_core_algorithms_export.h
mqt/core/include/mqt-core/boost/config.hpp
mqt/core/include/mqt-core/boost/cstdint.hpp
mqt/core/include/mqt-core/boost/cxx11_char_types.hpp
mqt/core/include/mqt-core/boost/limits.hpp
mqt/core/include/mqt-core/boost/version.hpp
mqt/core/include/mqt-core/boost/config/abi_prefix.hpp
mqt/core/include/mqt-core/boost/config/abi_suffix.hpp
mqt/core/include/mqt-core/boost/config/assert_cxx03.hpp
mqt/core/include/mqt-core/boost/config/assert_cxx11.hpp
mqt/core/include/mqt-core/boost/config/assert_cxx14.hpp
mqt/core/include/mqt-core/boost/config/assert_cxx17.hpp
mqt/core/include/mqt-core/boost/config/assert_cxx20.hpp
mqt/core/include/mqt-core/boost/config/assert_cxx23.hpp
mqt/core/include/mqt-core/boost/config/assert_cxx98.hpp
mqt/core/include/mqt-core/boost/config/auto_link.hpp
mqt/core/include/mqt-core/boost/config/header_deprecated.hpp
mqt/core/include/mqt-core/boost/config/helper_macros.hpp
mqt/core/include/mqt-core/boost/config/pragma_message.hpp
mqt/core/include/mqt-core/boost/config/requires_threads.hpp
mqt_core-3.4.0.dist-info/METADATA
mqt_core-3.4.0.dist-info/WHEEL
mqt_core-3.4.0.dist-info/entry_points.txt
mqt_core-3.4.0.dist-info/RECORD
mqt_core-3.4.0.dist-info/licenses/LICENSE.md
