Metadata-Version: 2.4
Name: mqt-core
Version: 3.4.0
Summary: The Backbone of the Munich Quantum Toolkit
Keywords: MQT,quantum-computing,design-automation,decision-diagrams,zx-calculus
Author-Email: Lukas Burgholzer <burgholzer@me.com>
License-Expression: MIT
License-File: LICENSE.md
Classifier: Development Status :: 5 - Production/Stable
Classifier: Intended Audience :: Science/Research
Classifier: Natural Language :: English
Classifier: Operating System :: MacOS
Classifier: Operating System :: Microsoft :: Windows
Classifier: Operating System :: POSIX :: Linux
Classifier: Programming Language :: C++
Classifier: Programming Language :: Python
Classifier: Programming Language :: Python :: 3
Classifier: Programming Language :: Python :: 3 :: Only
Classifier: Programming Language :: Python :: 3.10
Classifier: Programming Language :: Python :: 3.11
Classifier: Programming Language :: Python :: 3.12
Classifier: Programming Language :: Python :: 3.13
Classifier: Programming Language :: Python :: 3.14
Classifier: Topic :: Scientific/Engineering :: Electronic Design Automation (EDA)
Classifier: Typing :: Typed
Project-URL: Homepage, https://github.com/munich-quantum-toolkit/core
Project-URL: Changelog, https://github.com/munich-quantum-toolkit/core/blob/main/CHANGELOG.md
Project-URL: Documentation, https://mqt.readthedocs.io/projects/core
Project-URL: Issues, https://github.com/munich-quantum-toolkit/core/issues
Project-URL: Discussions, https://github.com/munich-quantum-toolkit/core/discussions
Project-URL: PyPI, https://pypi.org/project/mqt-core/
Requires-Python: >=3.10
Provides-Extra: qiskit
Requires-Dist: qiskit[qasm3-import]>=1.0.0; extra == "qiskit"
